terminal_radio/__init__.py
terminal_radio/radio.py
terminal_radio/stations.m3u
vintage_radio-1.0.0.dist-info/METADATA
vintage_radio-1.0.0.dist-info/WHEEL
vintage_radio-1.0.0.dist-info/entry_points.txt
vintage_radio-1.0.0.dist-info/RECORD
