Metadata-Version: 2.4
Name: vintage-radio
Version: 1.0.0
Summary: A retro-style internet radio player for the terminal
Project-URL: Homepage, https://github.com/philjung/terminal-radio
Author: Phil Jung
License-Expression: MIT
Keywords: music,radio,streaming,terminal,tui
Classifier: Development Status :: 4 - Beta
Classifier: Environment :: Console
Classifier: Intended Audience :: End Users/Desktop
Classifier: License :: OSI Approved :: MIT License
Classifier: Operating System :: MacOS
Classifier: Operating System :: POSIX :: Linux
Classifier: Programming Language :: Python :: 3
Classifier: Programming Language :: Python :: 3.9
Classifier: Programming Language :: Python :: 3.10
Classifier: Programming Language :: Python :: 3.11
Classifier: Programming Language :: Python :: 3.12
Classifier: Topic :: Multimedia :: Sound/Audio :: Players
Requires-Python: >=3.9
Requires-Dist: python-mpv>=1.0.0
Requires-Dist: textual>=0.40.0
